pyampd/__init__.py
pyampd/ampd.py
pyampd-0.0.1.dist-info/LICENSE
pyampd-0.0.1.dist-info/METADATA
pyampd-0.0.1.dist-info/WHEEL
pyampd-0.0.1.dist-info/entry_points.txt
pyampd-0.0.1.dist-info/top_level.txt
pyampd-0.0.1.dist-info/RECORD
