Metadata-Version: 2.1
Name: pyampd
Version: 0.0.1
Summary: Peak detection using AMPD and ASS-AMPD algorithms
Home-page: https://github.com/ig248/pyampd
Author: Igor Gotlibovych
Author-email: igor.gotlibovych@gmail.com
License: MIT
Platform: UNKNOWN
Classifier: Intended Audience :: Developers
Classifier: Operating System :: OS Independent
Classifier: Programming Language :: Python
Classifier: Programming Language :: Python :: 3
Classifier: Programming Language :: Python :: 3.6
Requires-Dist: numpy
Requires-Dist: scipy
